Modules/Simulator.py
Modules/__init__.py
Modules/cli.py
gbmsimulator-0.0.4.dist-info/METADATA
gbmsimulator-0.0.4.dist-info/WHEEL
gbmsimulator-0.0.4.dist-info/entry_points.txt
gbmsimulator-0.0.4.dist-info/RECORD
