Metadata-Version: 2.1
Name: GBMSimulator
Version: 0.0.4
Summary: A minimalist package to simulate geometric brownian motion
Author: Andriy Sinclair
Requires-Python: >=3.12,<4.0
Classifier: Programming Language :: Python :: 3
Classifier: Programming Language :: Python :: 3.12
Classifier: Programming Language :: Python :: 3.13
Requires-Dist: matplotlib (>=3.9,<4.0)
Requires-Dist: numpy (>=2.1,<3.0)
Requires-Dist: sphinx-argparse (>=0.5.0,<0.6.0)
